Metadata-Version: 1.0
Name: django-mailchimp
Version: 0.1.30
Summary: Mailchimp wrapper for Django
Home-page: http://github.com/piquadrat/django-mailchimp
Author: Jonas Obrist et al.
Author-email: UNKNOWN
License: UNKNOWN
Platform: UNKNOWN
